MANIFEST.in
setup.cfg
setup.py
versioneer.py
uvio/__init__.py
uvio/_loop.c
uvio/_version.py
uvio/buffer_utils.py
uvio/fs.c
uvio/futures.py
uvio/handle.c
uvio/idle.c
uvio/loop.py
uvio/net.c
uvio/pipes.c
uvio/request.c
uvio/stream.c
uvio/subprocess.c
uvio/timer.c
uvio/tls.py
uvio/workers.c
uvio.egg-info/PKG-INFO
uvio.egg-info/SOURCES.txt
uvio.egg-info/dependency_links.txt
uvio.egg-info/top_level.txt
uvio/http/__init__.py
uvio/http/client.py
uvio/tests/__init__.py
uvio/tests/test_coroutines.py
uvio/tests/test_fs.py
uvio/tests/test_futures.py
uvio/tests/test_http.py
uvio/tests/test_idle.py
uvio/tests/test_loop.py
uvio/tests/test_net.py
uvio/tests/test_pipes.py
uvio/tests/test_process.py
uvio/tests/test_timer.py
uvio/tests/test_worker.py