Metadata-Version: 1.0
Name: uvio
Version: 0.0.1
Summary: asyncio replacement library using libuv
Home-page: http://github.com/srossross/uvio
Author: Sean Ross-Ross
Author-email: srossross@gmail.com
License: UNKNOWN
Platform: UNKNOWN
